{
  "project_info": {
    "project_number": "501896777883",
    "project_id": "rockethelp-367dd",
    "storage_bucket": "rockethelp-367dd.appspot.com"
  },
  "client": [
    {
      "client_info": {
        "mobilesdk_app_id": "1:501896777883:android:0772ea09f9a6a59669363e",
        "android_client_info": {
          "package_name": "com.caducoder.rockethelp"
        }
      },
      "oauth_client": [
        {
          "client_id": "501896777883-gc7uhcsr7rjj2166mv6r8qkl18p0hn5d.apps.googleusercontent.com",
          "client_type": 3
        }
      ],
      "api_key": [
        {
          "current_key": "AIzaSyBHGbPMQDBRUJ7zxn9a93btygH3ToJiEI0"
        }
      ],
      "services": {
        "appinvite_service": {
          "other_platform_oauth_client": [
            {
              "client_id": "501896777883-gc7uhcsr7rjj2166mv6r8qkl18p0hn5d.apps.googleusercontent.com",
              "client_type": 3
            }
          ]
        }
      }
    }
  ],
  "configuration_version": "1"
}